{
    "1": {
        "description": [
            "Supply of Central Bank Reserves and Bank Asset Illiquidity.This figure plots the total reserves of US depository institutions and their ratio of illiquid to total assets from 1990 to 2021. Illiquid assets include all assets except for cash, reserves, Fed funds, repos, Treasury securities and agency securities. Data is from FRED."
        ],
        "correlation": []
    },
    "2": {
        "description": [
            "This figure illustrates the effect of an increase in reserves on the loan market. An increase in reserve supply shifts the bank’s marginal cost curve for lending. This results in a new intersection with the marginal revenue curve, yielding a new interest rate, RL′. The new loan quantity, QL′, is then pinned down by the demand curve."
        ],
        "correlation": []
    },
    "3": {
        "description": [
            "Observed and Counterfactual Lending Quantities."
        ],
        "correlation": []
    },
    "4": {
        "description": [
            "Reserve Supply and Reduction in Corporate Loan Issuance."
        ],
        "correlation": []
    },
    "5": {
        "description": [
            "IOER-Fed Funds Spread and Model-Implied Reserve Spread."
        ],
        "correlation": []
    }
}